djangokit/Base.py
djangokit/Host.py
djangokit/Template.py
djangokit/VercelKit.py
djangokit/__init__.py
djangokit/templatetage.py
DJOptima-0.0.1.dist-info/LICENCE.txt
DJOptima-0.0.1.dist-info/METADATA
DJOptima-0.0.1.dist-info/WHEEL
DJOptima-0.0.1.dist-info/entry_points.txt
DJOptima-0.0.1.dist-info/top_level.txt
DJOptima-0.0.1.dist-info/RECORD
